liffpy/__about__.py
liffpy/__init__.py
liffpy/api.py
liffpy-0.0.1a3.dist-info/METADATA
liffpy-0.0.1a3.dist-info/RECORD
liffpy-0.0.1a3.dist-info/WHEEL
liffpy-0.0.1a3.dist-info/top_level.txt
