Metadata-Version: 2.1
Name: liffpy
Version: 0.0.1a3
Summary: It is a package that allows you to manipulate LIFF(Line Frontend Framework) by Python.
Home-page: https://github.com/fantm21/liffpy
Author: FumiyaOgawa
Author-email: engineer.fumi@gmail.com
License: Apache License 2.0
Platform: UNKNOWN
Classifier: Development Status :: 2 - Pre-Alpha
Classifier: License :: OSI Approved :: Apache Software License
Classifier: Intended Audience :: Developers
Classifier: Programming Language :: Python
Classifier: Programming Language :: Python :: 3
Classifier: Programming Language :: Python :: 3.3
Classifier: Programming Language :: Python :: 3.4
Classifier: Programming Language :: Python :: 3.5
Classifier: Programming Language :: Python :: 3.6
Classifier: Topic :: Software Development
